{
  "sites": [
    {
      "name": "if101(海外推荐)",
      "type": 3,
      "page": 1,
      "url": "https://demo.if101.tv/api.php/provide/vod/at/xml",
      "categories": {
        "体育": 24,
        "纪录片": 25,
        "冒险片": 28,
        "剧情片": 29,
        "动作片": 30,
        "动画电影": 31,
        "同性片": 32,
        "喜剧片": 33,
        "奇幻片": 34,
        "恐怖片": 35,
        "悬疑片": 36,
        "惊悚片": 37,
        "歌舞片": 38,
        "灾难片": 39,
        "爱情片": 40,
        "犯罪片": 41,
        "科幻片": 42,
        "经典片": 43,
        "网络电影": 44,
        "战争片": 117,
        "欧美剧": 119,
        "日剧": 120,
        "韩剧": 121,
        "国产剧": 122,
        "泰剧": 123,
        "港剧": 124,
        "台剧": 125,
        "新马剧": 126,
        "其他剧": 127,
        "欧美综艺": 128,
        "日本综艺": 129,
        "韩国综艺": 130,
        "国产综艺": 131,
        "新马泰综艺": 132,
        "港台综艺": 133,
        "其他综艺": 134,
        "欧美动漫": 135,
        "日本动漫": 136,
        "韩国动漫": 137,
        "国产动漫": 138,
        "新马泰动漫": 139,
        "港台动漫": 140,
        "其他动漫": 142
    },
    {
      "name": "江湖官采(官)",
      "type": 3,
      "page": 1,
      "url": "http://119.29.1.173/api.php/provide/vod/at/xml",
      "categories": {
        "电影": 1,
        "连续剧": 2,
        "综艺": 3,
        "动漫": 4
    }
  ]
}
